climatic_regions/__init__.py
climatic_regions/_version.py
climatic_regions/annual_agera_embeddings_v1/__init__.py
climatic_regions/annual_agera_embeddings_v1/meteo_biomes_2018.tif
climatic_regions/annual_agera_embeddings_v1/meteo_biomes_2019.tif
climatic_regions/annual_agera_embeddings_v1/meteo_biomes_2020.tif
climatic_regions/annual_agera_embeddings_v1/meteo_biomes_2021.tif
climatic_regions/annual_agera_embeddings_v1/meteo_biomes_2022.tif
climatic_regions/annual_agera_embeddings_v1/meteo_biomes_2023.tif
climatic_regions-0.0.4.dist-info/METADATA
climatic_regions-0.0.4.dist-info/WHEEL
climatic_regions-0.0.4.dist-info/RECORD
