Metadata-Version: 2.4
Name: climatic-regions
Version: 0.0.4
Summary: AgERA5 Climatic Regions Embeddings
Author: VITO RS Vegetation team
Classifier: Operating System :: OS Independent
Classifier: Programming Language :: Python :: 3
Requires-Python: >=3.8
Requires-Dist: geopandas>=0.13.2
Requires-Dist: numpy>=1.24.4
Requires-Dist: rasterio>=1.3.11
Requires-Dist: rio-tiler>=7.2.2
Requires-Dist: scikit-image>=0.21.0
Requires-Dist: shapely>=2.0.7
